pdf2ocr/__init__.py
pdf2ocr/__main__.py
pdf2ocr/config.py
pdf2ocr/converters.py
pdf2ocr/logging_config.py
pdf2ocr/main.py
pdf2ocr/ocr.py
pdf2ocr/state.py
pdf2ocr/utils.py
pdf2ocr/converters/__init__.py
pdf2ocr/converters/common.py
pdf2ocr/converters/docx.py
pdf2ocr/converters/epub.py
pdf2ocr/converters/html.py
pdf2ocr/converters/pdf.py
pdf2ocr-1.0.19.dist-info/licenses/AUTHORS
pdf2ocr-1.0.19.dist-info/licenses/LICENSE
pdf2ocr-1.0.19.dist-info/METADATA
pdf2ocr-1.0.19.dist-info/WHEEL
pdf2ocr-1.0.19.dist-info/entry_points.txt
pdf2ocr-1.0.19.dist-info/top_level.txt
pdf2ocr-1.0.19.dist-info/RECORD
