Metadata-Version: 2.4
Name: pdf2ocr
Version: 1.0.19
Summary: A CLI tool to apply OCR on PDF files and export to multiple formats.
Author: Rafael Dantas
License: MIT
Requires-Python: >=3.6
License-File: LICENSE
License-File: AUTHORS
Requires-Dist: pytesseract>=0.3.10
Requires-Dist: pdf2image>=1.16.0
Requires-Dist: python-docx>=0.8.11
Requires-Dist: reportlab>=4.0.0
Requires-Dist: tqdm>=4.45.0
Requires-Dist: Pillow>=9.0.0
Requires-Dist: pypdf>=3.15.0
Dynamic: author
Dynamic: description
Dynamic: description-content-type
Dynamic: license
Dynamic: license-file
Dynamic: requires-dist
Dynamic: requires-python
Dynamic: summary
